pricing_gym/__init__.py
pricing_gym/envs/__init__.py
pricing_gym/envs/pricing.py
pricing_gym/envs/toy_pricing.py
pricing_gym/wrappers/__init__.py
pricing_gym-0.2.0.dist-info/METADATA
pricing_gym-0.2.0.dist-info/WHEEL
pricing_gym-0.2.0.dist-info/top_level.txt
pricing_gym-0.2.0.dist-info/RECORD
